adafruit_opt4048.py
adafruit_circuitpython_opt4048-1.1.0.dist-info/licenses/LICENSE
adafruit_circuitpython_opt4048-1.1.0.dist-info/METADATA
adafruit_circuitpython_opt4048-1.1.0.dist-info/WHEEL
adafruit_circuitpython_opt4048-1.1.0.dist-info/top_level.txt
adafruit_circuitpython_opt4048-1.1.0.dist-info/RECORD
