Metadata-Version: 2.4
Name: adafruit-circuitpython-opt4048
Version: 1.1.0
Summary: CircuitPython driver library for the Adafruit OPT4048 breakout board, a high-speed, high-precision tristimulus XYZ color sensor.
Author-email: Adafruit Industries <circuitpython@adafruit.com>
License: MIT
Project-URL: Homepage, https://github.com/adafruit/Adafruit_CircuitPython_OPT4048
Keywords: adafruit,blinka,circuitpython,micropython,opt4048,color,colorsensor,sensor,colors,light,lux,xyz,tristimulus
Classifier: Intended Audience :: Developers
Classifier: Topic :: Software Development :: Libraries
Classifier: Topic :: Software Development :: Embedded Systems
Classifier: Topic :: System :: Hardware
Classifier: License :: OSI Approved :: MIT License
Classifier: Programming Language :: Python :: 3
License-File: LICENSE
Requires-Dist: Adafruit-Blinka
Requires-Dist: adafruit-circuitpython-busdevice
Requires-Dist: adafruit-circuitpython-register
Provides-Extra: optional
Dynamic: license-file
